{
  "id": "IpbAn73Uo",
  "propertyId": "zlqQNxLcGh",
  "title": "Most Recent TG",
  "description": "Please Edit description for Page \"Variant 5\"",
  "enabledPagesId": [
    "dEuNmasA7"
  ],
  "isPage": true,
  "blocks": [
    {
      "id": "xP8_NyBfmv",
      "condition": "*",
      "title": "Most Recent TG",
      "type": "nested",
      "layout": {
        "i": "xP8_NyBfmv",
        "x": 0,
        "y": 1,
        "w": 12,
        "h": 30,
        "blocks": []
      },
      "results": {
        "flatAllBlocks": true
      },
      "blockId": "efMPssH74G",
      "metadataUI": {
        "attributes": {
          "template": "KEYFRAME"
        }
      }
    }
  ],
  "version": 5,
  "lastSaved": {
    "username": "giulia.miotto",
    "date": "2022-06-16T14:58:25.144Z"
  },
  "refs": {
    "belongs": [
      {
        "type": "endpoints",
        "items": [
          "dEuNmasA7"
        ]
      },
      {
        "type": "blocks",
        "items": [
          "eSZgKCzVb"
        ]
      }
    ],
    "require": [
      {
        "type": "queries",
        "items": []
      },
      {
        "type": "endpoints",
        "items": []
      },
      {
        "type": "blocks",
        "items": [
          "efMPssH74G"
        ]
      },
      {
        "type": "lists",
        "items": []
      },
      {
        "type": "labels",
        "items": []
      },
      {
        "type": "responseFields",
        "items": []
      },
      {
        "type": "externalSources",
        "items": []
      }
    ]
  },
  "refsComputed": {
    "belongs": {
      "total": 1,
      "types": 1,
      "items": [
        {
          "type": "endpoints",
          "count": 1,
          "items": [
            {
              "id": "dEuNmasA7",
              "type": "endpoints"
            }
          ]
        }
      ]
    },
    "require": {
      "total": 1,
      "types": 7,
      "items": [
        {
          "type": "queries",
          "count": 0,
          "items": []
        },
        {
          "type": "endpoints",
          "count": 0,
          "items": []
        },
        {
          "type": "blocks",
          "count": 1,
          "items": [
            {
              "id": "efMPssH74G",
              "type": "blocks"
            }
          ]
        },
        {
          "type": "lists",
          "count": 0,
          "items": []
        },
        {
          "type": "labels",
          "count": 0,
          "items": []
        },
        {
          "type": "responseFields",
          "count": 0,
          "items": []
        },
        {
          "type": "externalSources",
          "count": 0,
          "items": []
        }
      ]
    }
  },
  "layout": [
    {
      "i": "xP8_NyBfmv",
      "x": 0,
      "y": 1,
      "w": 12,
      "h": 30,
      "blocks": []
    }
  ],
  "canBeFallback": true
}