{
  "refs": {
    "require": [
      {
        "type": "queries",
        "items": [
          "QniVzl_vg"
        ]
      },
      {
        "type": "endpoints",
        "items": []
      },
      {
        "type": "blocks",
        "items": []
      },
      {
        "type": "lists",
        "items": []
      },
      {
        "type": "labels",
        "items": []
      },
      {
        "type": "responseFields",
        "items": [
          "eOaXizx_"
        ]
      },
      {
        "type": "externalSources",
        "items": []
      }
    ],
    "belongs": [
      {
        "type": "blocks",
        "items": [
          "H5LkUZTLLD"
        ]
      }
    ]
  },
  "refsComputed": {
    "belongs": {
      "total": 1,
      "types": 1,
      "items": [
        {
          "type": "pages",
          "count": 1,
          "items": [
            {
              "variantId": "H5LkUZTLLD",
              "propertyId": "zlqQNxLcGh",
              "propertyTitle": "",
              "endpointId": "QWy8y_ZIwz",
              "endpointTitle": ""
            }
          ]
        }
      ]
    },
    "require": {
      "total": 2,
      "types": 7,
      "items": [
        {
          "type": "queries",
          "count": 1,
          "items": [
            {
              "id": "QniVzl_vg",
              "type": "queries",
              "title": ""
            }
          ]
        },
        {
          "type": "endpoints",
          "count": 0,
          "items": []
        },
        {
          "type": "blocks",
          "count": 0,
          "items": []
        },
        {
          "type": "lists",
          "count": 0,
          "items": []
        },
        {
          "type": "labels",
          "count": 0,
          "items": []
        },
        {
          "type": "responseFields",
          "count": 1,
          "items": [
            {
              "id": "eOaXizx_",
              "type": "responseFields",
              "title": ""
            }
          ]
        },
        {
          "type": "externalSources",
          "count": 0,
          "items": []
        }
      ]
    }
  },
  "results": {
    "flatAllBlocks": true,
    "min": 0
  },
  "blocks": [
    {
      "_id": "FHfKWUKT1O",
      "condition": "*",
      "title": "Clip più viste 24h",
      "type": "query",
      "pinned": true,
      "results": {
        "max": 20,
        "min": 0,
        "contentType": "video",
        "responseFieldsId": "eOaXizx_"
      },
      "queryId": "QniVzl_vg"
    }
  ],
  "scheduled": false,
  "scheduling": [],
  "schedulingMap": [],
  "realm": "content",
  "title": "Block Fallback per Similar No Category",
  "description": "Endpoint similarNoCategory - blocco utilizzato come valore Similar di default nel caso in cui non ci sia una uxReference corrispondente alla categoria del contenuto.",
  "canBeFallback": true,
  "id": "VwthsCrnw",
  "version": 2,
  "lastSaved": {
    "username": "giulia.miotto",
    "date": "2022-08-22T09:34:44.458Z"
  }
}