{
  "title": "SRC Fallback Search Video Gratis per te",
  "description": "",
  "contentType": "video",
  "filter": [
    {
      "id": "ju06OqIgO"
    },
    {
      "id": "_lqe9hGoC"
    }
  ],
  "exclude": [],
  "include": [],
  "boost": [],
  "order": [
    {
      "id": "SXyaET7iz2"
    }
  ],
  "realm": "content",
  "refs": {
    "require": [
      {
        "type": "rules",
        "items": [
          "ju06OqIgO",
          "_lqe9hGoC",
          "SXyaET7iz2"
        ]
      },
      {
        "type": "rulesPresets",
        "items": [
          "ZRorAbL96Q"
        ]
      }
    ],
    "belongs": [
      {
        "type": "blocks",
        "items": [
          "bwz88ulRY"
        ]
      }
    ]
  },
  "general": {
    "minimumShouldMatch": "1%",
    "tieBreaker": 0.9,
    "resultsMultiplier": 1
  },
  "id": "V89qJLPCh",
  "version": 4,
  "lastSaved": {
    "username": "Giuseppe.Carroccio",
    "date": "2023-01-20T15:23:00.615Z"
  },
  "refsComputed": {
    "belongs": {
      "total": 1,
      "types": 1,
      "items": [
        {
          "type": "blocks",
          "count": 1,
          "items": [
            {
              "id": "bwz88ulRY",
              "type": "blocks",
              "title": ""
            }
          ]
        }
      ]
    },
    "require": {
      "total": 3,
      "types": 2,
      "items": [
        {
          "type": "rules",
          "count": 3,
          "items": [
            {
              "id": "ju06OqIgO",
              "type": "rules",
              "title": ""
            },
            {
              "id": "_lqe9hGoC",
              "type": "rules",
              "title": ""
            },
            {
              "id": "SXyaET7iz2",
              "type": "rules",
              "title": ""
            }
          ]
        },
        {
          "type": "rulesPresets",
          "count": 0,
          "items": []
        }
      ]
    }
  },
  "presets": {
    "exclude": [
      {
        "id": "ZRorAbL96Q"
      }
    ]
  }
}